vai_lab/__init__.py
vai_lab/_import_helper.py
vai_lab/_plugin_helpers.py
vai_lab/_plugin_templates.py
vai_lab/_types.py
vai_lab/run_pipeline.py
vai_lab/Core/__init__.py
vai_lab/Core/vai_lab_core.py
vai_lab/Core/Assets/UFAIcon.ico
vai_lab/Core/Assets/UFAIcon_name.png
vai_lab/Core/tests/__init__.py
vai_lab/Core/tests/test_vai_lab_core.py
vai_lab/Data/Data_core.py
vai_lab/Data/__init__.py
vai_lab/Data/xml_handler.py
vai_lab/Data/tests/__init__.py
vai_lab/DataProcessing/DataProcessing_core.py
vai_lab/DataProcessing/__init__.py
vai_lab/DataProcessing/plugins/binarizer.py
vai_lab/DataProcessing/plugins/kbinsdiscretizer.py
vai_lab/DataProcessing/plugins/labelbinarizer.py
vai_lab/DataProcessing/plugins/labelencoder.py
vai_lab/DataProcessing/plugins/maxabsscaler.py
vai_lab/DataProcessing/plugins/minmaxscaler.py
vai_lab/DataProcessing/plugins/multilabelbinarizer.py
vai_lab/DataProcessing/plugins/normalizer.py
vai_lab/DataProcessing/plugins/onehotencoder.py
vai_lab/DataProcessing/plugins/ordinalencoder.py
vai_lab/DataProcessing/plugins/polynomialfeatures.py
vai_lab/DataProcessing/plugins/quantiletransformer.py
vai_lab/DataProcessing/plugins/standardscaler.py
vai_lab/DataProcessing/tests/__init__.py
vai_lab/DataStorage/DataStorage_core.py
vai_lab/DataStorage/__init__.py
vai_lab/DataStorage/tests/__init__.py
vai_lab/DecisionMaking/Modelling_core.py
vai_lab/DecisionMaking/__init__.py
vai_lab/DecisionMaking/tests/__init__.py
vai_lab/Environment/Environment_core.py
vai_lab/Environment/plugins/PyBulletEnv.py
vai_lab/Environment/resources/models/half_cheetah.xml
vai_lab/Environment/resources/models/half_cheetah_with_mass.xml
vai_lab/Environment/tests/__init__.py
vai_lab/GUI/GUI_core.py
vai_lab/GUI/User_Feedback_template.py
vai_lab/GUI/__init__.py
vai_lab/GUI/plugins/__init__.py
vai_lab/GUI/tests/__init__.py
vai_lab/InputData/InputData_core.py
vai_lab/InputData/__init__.py
vai_lab/InputData/tests/__init__.py
vai_lab/Modelling/Modelling_core.py
vai_lab/Modelling/__init__.py
vai_lab-0.0.dev4.dist-info/entry_points.txt
vai_lab-0.0.dev4.dist-info/WHEEL
vai_lab-0.0.dev4.dist-info/METADATA
vai_lab-0.0.dev4.dist-info/RECORD
