Metadata-Version: 2.1
Name: vai_lab
Version: 0.0.dev4
Summary: AI assisted Virtual Laboratory framework.
Author-email: Chris McGreavy <chris.mcgreavy@aalto.fi>, Carlos Sevilla Salcedo <carlos.sevillasalcedo@aalto.fi>
Requires-Python: >=3.8
Classifier: License :: OSI Approved :: MIT License
Classifier: Programming Language :: Python :: 3.8
Classifier: Programming Language :: Python :: 3.9
Classifier: Programming Language :: Python :: 3.10
Classifier: Programming Language :: Python :: 3.11
Requires-Dist: numpy >= 1.20.0
Requires-Dist: pillow >= 9.0.0
Requires-Dist: pandas >= 1.4.0
Requires-Dist: sklearn >= 0.0
Requires-Dist: ttkwidgets >= 0.12.0
Requires-Dist: matplotlib >= 3.5.0
Requires-Dist: opencv-python >= 4.6.0.65
Requires-Dist: pytest >= 7.2.0
Project-URL: Source, https://github.com/AaltoPML/VAI-lab
